pygments_style_spacemacs/__init__.py
pygments_style_spacemacs/spacemacs_dark.py
pygments_style_spacemacs/spacemacs_light.py
pygments_style_spacemacs-1.0.0.1.dist-info/LICENSE
pygments_style_spacemacs-1.0.0.1.dist-info/METADATA
pygments_style_spacemacs-1.0.0.1.dist-info/WHEEL
pygments_style_spacemacs-1.0.0.1.dist-info/entry_points.txt
pygments_style_spacemacs-1.0.0.1.dist-info/top_level.txt
pygments_style_spacemacs-1.0.0.1.dist-info/RECORD
